mcp_checkpoint/__init__.py
mcp_checkpoint/cli.py
mcp_checkpoint/connector.py
mcp_checkpoint/run_checks.py
mcp_checkpoint/scanner.py
mcp_checkpoint/security_utils.py
mcp_checkpoint/scan_checks/__init__.py
mcp_checkpoint/scan_checks/command_injection.py
mcp_checkpoint/scan_checks/cross_server_tool_shadowing.py
mcp_checkpoint/scan_checks/excessive_tool_permissions.py
mcp_checkpoint/scan_checks/hardcoded_secrets.py
mcp_checkpoint/scan_checks/prompt_injection.py
mcp_checkpoint/scan_checks/tool_name_ambiguity.py
mcp_checkpoint-1.0.0.dist-info/licenses/LICENSE
mcp_checkpoint-1.0.0.dist-info/METADATA
mcp_checkpoint-1.0.0.dist-info/WHEEL
mcp_checkpoint-1.0.0.dist-info/entry_points.txt
mcp_checkpoint-1.0.0.dist-info/top_level.txt
mcp_checkpoint-1.0.0.dist-info/RECORD
