Metadata-Version: 2.4
Name: mcp-checkpoint
Version: 1.0.0
Summary: A comprehensive MCP configuration scanner with client-aware security analysis
Author-email: Aira Security <founders@airasecurity.ai>
License-Expression: Apache-2.0
Project-URL: Homepage, https://github.com/aira-security/mcp-checkpoint
Project-URL: Repository, https://github.com/aira-security/mcp-checkpoint
Project-URL: Issues, https://github.com/aira-security/mcp-checkpoint/issues
Classifier: Development Status :: 5 - Production/Stable
Classifier: Intended Audience :: Developers
Classifier: Operating System :: OS Independent
Classifier: Programming Language :: Python :: 3
Classifier: Programming Language :: Python :: 3.8
Classifier: Programming Language :: Python :: 3.9
Classifier: Programming Language :: Python :: 3.10
Classifier: Programming Language :: Python :: 3.11
Classifier: Programming Language :: Python :: 3.12
Requires-Python: >=3.8
License-File: LICENSE
Requires-Dist: fastmcp>=2.13.0
Requires-Dist: pyyaml>=6.0.2
Requires-Dist: thefuzz>=0.22.1
Requires-Dist: rich>=14.1.0
Requires-Dist: transformers==4.57.1
Requires-Dist: torch==2.9.0
Dynamic: license-file
